tagoapi/__init__.py
tagoapi/auth.py
tagoapi/client.py
tagoapi/exceptions.py
tagoapi/caches/cache.pkl
tagoapi/caches/station.pkl
tagoapi/models/ArrivalInfo.py
tagoapi/models/BaseModel.py
tagoapi/models/Route.py
tagoapi/models/Station.py
tagoapi/models/Vehicle.py
tagoapi/models/__init__.py
tagoapi/utils/__init__.py
tagoapi/utils/cache.py
tagoapi/utils/cache_util.py
tagoapi/utils/convertor.py
tagoapi/utils/get_station.py
tagoapi/utils/http.py
tagoapi/utils/params.py
tagoapi/utils/parser.py
tagoapi/utils/utils.py
unoffical_tago_api-0.12.dist-info/licenses/LICENSE
unoffical_tago_api-0.12.dist-info/METADATA
unoffical_tago_api-0.12.dist-info/WHEEL
unoffical_tago_api-0.12.dist-info/top_level.txt
unoffical_tago_api-0.12.dist-info/RECORD
