Metadata-Version: 2.4
Name: UnOffical_TAGO_API
Version: 0.12
Summary: Unofficial Python wrapper for TAGO Bus API
Home-page: https://github.com/hyuntroll/TAGOBus-API
Author: hyuntroll
Author-email: hsm200905292@gmail.com
License: MIT
License-File: LICENSE
Requires-Dist: requests
Requires-Dist: xmltodict
Dynamic: author
Dynamic: author-email
Dynamic: description
Dynamic: description-content-type
Dynamic: home-page
Dynamic: license
Dynamic: license-file
Dynamic: requires-dist
Dynamic: summary
